CHANGES
LICENSE
MANIFEST.in
README.rst
setup.py
bumpr_testing_storborg/__init__.py
bumpr_testing_storborg.egg-info/PKG-INFO
bumpr_testing_storborg.egg-info/SOURCES.txt
bumpr_testing_storborg.egg-info/dependency_links.txt
bumpr_testing_storborg.egg-info/not-zip-safe
bumpr_testing_storborg.egg-info/top_level.txt
bumpr_testing_storborg/tests/__init__.py
bumpr_testing_storborg/tests/test_anything.py