Metadata-Version: 1.1
Name: bumpr-testing-storborg
Version: 0.0.2
Summary: Testing bumpr.rc
Home-page: https://github.com/storborg/bumpr_testing_storborg
Author: Scott Torborg
Author-email: storborg@gmail.com
License: GPL
Keywords: bumpr test
Platform: UNKNOWN
Classifier: Development Status :: 3 - Alpha
Classifier: License :: OSI Approved :: GNU General Public License (GPL)
Classifier: Programming Language :: Python :: 3
Classifier: Programming Language :: Python :: 3.6
